mitty/__init__.py
mitty/cli.py
mitty/version.py
mitty/analysis/__init__.py
mitty/analysis/aaftoolz.py
mitty/analysis/bamfilters.py
mitty/analysis/bamhist.py
mitty/analysis/bamtoolz.py
mitty/analysis/plots.py
mitty/benchmarking/__init__.py
mitty/benchmarking/alignmentscore.py
mitty/benchmarking/bam_to_truth.py
mitty/benchmarking/callfate.py
mitty/benchmarking/complexity.py
mitty/benchmarking/evcfbysize.py
mitty/benchmarking/filterevalvcf.py
mitty/benchmarking/god_aligner.py
mitty/benchmarking/partition_bams.py
mitty/benchmarking/subsetbam.py
mitty/benchmarking/vsizedistrib.py
mitty/benchmarking/xmv.py
mitty/benchmarking/plot/__init__.py
mitty/benchmarking/plot/byvsize.py
mitty/benchmarking/plot/placeholderfigure.py
mitty/data/readmodels/1kg-pcr-free.pkl
mitty/data/readmodels/hiseq-2500-v1-pcr-free.pkl
mitty/data/readmodels/hiseq-X-v1-HLI.pkl
mitty/data/readmodels/hiseq-X-v2.5-Garvan.pkl
mitty/data/readmodels/illuminaHiSeq-FCA.pkl
mitty/data/readmodels/old-Garvan.pkl
mitty/empirical/__init__.py
mitty/empirical/bam2illumina.py
mitty/empirical/bq.py
mitty/empirical/bq_fastq.py
mitty/empirical/gc.py
mitty/empirical/qnamestats.py
mitty/empirical/qnametruncate.py
mitty/lib/__init__.py
mitty/lib/bamfetch.py
mitty/lib/bedfile.py
mitty/lib/cigars.py
mitty/lib/evcfparse.py
mitty/lib/sanitizeseq.py
mitty/lib/vcfio.py
mitty/simulation/__init__.py
mitty/simulation/illumina.py
mitty/simulation/readcorrupt.py
mitty/simulation/readgenerate.py
mitty/simulation/rpc.py
mitty/simulation/genome/__init__.py
mitty/simulation/genome/sampledgenome.py
mitty/simulation/genome/simulatevariants.py
mitty/simulation/sequencing/__init__.py
mitty/simulation/sequencing/flat_illumina.py
mitty/simulation/sequencing/syntheticsequencer.py
mitty/simulation/sequencing/writefastq.py
mitty/test/__init__.py
mitty/test/benchmarking/__init__.py
mitty/test/benchmarking/test_alignmentscore.py
mitty/test/benchmarking/test_complexity.py
mitty/test/data/flawed-tiny.vcf
mitty/test/data/flawed-tiny.vcf.gz
mitty-2.29.0.dist-info/LICENSE.txt
mitty-2.29.0.dist-info/METADATA
mitty-2.29.0.dist-info/WHEEL
mitty-2.29.0.dist-info/entry_points.txt
mitty-2.29.0.dist-info/top_level.txt
mitty-2.29.0.dist-info/RECORD
