Metadata-Version: 2.1
Name: mitty
Version: 2.29.0
Summary: Simulator for genomic data
Home-page: https://github.com/sbg/Mitty
Author: Seven Bridges Genomics
Author-email: kaushik.ghose@sbgdinc.com
License: UNKNOWN
Download-URL: https://github.com/sbg/Mitty/archive/development.zip
Keywords: simulator,genomics,ngs,read mapper,aligner,variant caller
Platform: UNKNOWN
Classifier: Development Status :: 5 - Production/Stable
Classifier: Intended Audience :: Science/Research
Classifier: Topic :: Scientific/Engineering :: Bio-Informatics
Classifier: License :: OSI Approved :: Apache Software License
Classifier: Programming Language :: Python :: 3.4
Requires-Python: >=3.4
Requires-Dist: cython
Requires-Dist: setuptools (>=24.3.0)
Requires-Dist: numpy (>=1.11.0)
Requires-Dist: click (>=3.3)
Requires-Dist: pysam (==0.10.0)
Requires-Dist: matplotlib (>=1.3.0)
Requires-Dist: scipy
Requires-Dist: pandas (>=0.20.3)
Requires-Dist: bokeh (>=0.12.13)
Requires-Dist: jupyter (>=1.0.0)
Requires-Dist: cytoolz
Requires-Dist: xarray (>=0.9.6)
Requires-Dist: nose
